setup.py
gym_renju/__init__.py
gym_renju.egg-info/PKG-INFO
gym_renju.egg-info/SOURCES.txt
gym_renju.egg-info/dependency_links.txt
gym_renju.egg-info/requires.txt
gym_renju.egg-info/top_level.txt
gym_renju/data/reward.json
gym_renju/data/test_reward.json
gym_renju/envs/__init__.py
gym_renju/envs/renju.py
gym_renju/envs/renju_container.py
gym_renju/envs/renju_env.py
gym_renju/envs/core/__init__.py
gym_renju/envs/core/contract/__init__.py
gym_renju/envs/core/contract/container.py
gym_renju/envs/core/contract/factory.py
gym_renju/envs/core/contract/policy.py
gym_renju/envs/core/contract/reward.py
gym_renju/envs/core/contract/rule_matcher.py
gym_renju/envs/core/contract/space.py
gym_renju/envs/core/domain/__init__.py
gym_renju/envs/core/domain/player.py
gym_renju/envs/core/domain/result.py
gym_renju/envs/core/domain/rule_pattern.py
gym_renju/envs/exception/__init__.py
gym_renju/envs/exception/invalid_type_exception.py
gym_renju/envs/policy/__init__.py
gym_renju/envs/policy/ai.py
gym_renju/envs/policy/input.py
gym_renju/envs/policy/policy_factory_impl.py
gym_renju/envs/rule/__init__.py
gym_renju/envs/rule/renju_reward.py
gym_renju/envs/rule/renju_rule_matcher.py
gym_renju/envs/rule/reward_factory_impl.py
gym_renju/envs/rule/rule.py
gym_renju/envs/rule/rule_matcher_factory_impl.py
gym_renju/envs/state/__init__.py
gym_renju/envs/state/renju_space.py
gym_renju/envs/state/space_factory_impl.py
gym_renju/envs/utils/__init__.py
gym_renju/envs/utils/generator.py
gym_renju/envs/utils/rule_pattern_compile.py
gym_renju/envs/utils/utils.py
gym_renju/test/__init__.py
gym_renju/test/renju_env_test.py
gym_renju/test/renju_test.py
gym_renju/test/rule_integration_test.py
gym_renju/test/policy/__init__.py
gym_renju/test/policy/policy_factory_test.py
gym_renju/test/rule/__init__.py
gym_renju/test/rule/renju_reward_test.py
gym_renju/test/rule/rule_pattern_compile_test.py
gym_renju/test/rule/rule_test.py
gym_renju/test/utils/__init__.py
gym_renju/test/utils/board_state_generator_test.py
gym_renju/test/utils/matcher_generator_test.py
gym_renju/test/utils/utils_test.py
sample/__init__.py
sample/sample.py