Metadata-Version: 1.1
Name: gym-renju
Version: 0.1.8
Summary: Renju Game Gym Environment
Home-page: UNKNOWN
Author: kkbnart
Author-email: UNKNOWN
License: MIT
Keywords: gym renju reinforcement learning
Platform: UNKNOWN
Classifier: Programming Language :: Python
Classifier: Programming Language :: Python :: 3.5
